sagemaker_studio_sparkmagic_lib/__init__.py
sagemaker_studio_sparkmagic_lib/cli.py
sagemaker_studio_sparkmagic_lib/emr.py
sagemaker_studio_sparkmagic_lib/kerberos.py
sagemaker_studio_sparkmagic_lib/sparkmagic.py
sagemaker_studio_sparkmagic_lib/utils.py
sagemaker_studio_sparkmagic_lib/data/sample_config.json
sagemaker_studio_sparkmagic_lib-0.1.4.dist-info/LICENSE
sagemaker_studio_sparkmagic_lib-0.1.4.dist-info/LICENSE.txt
sagemaker_studio_sparkmagic_lib-0.1.4.dist-info/METADATA
sagemaker_studio_sparkmagic_lib-0.1.4.dist-info/NOTICE
sagemaker_studio_sparkmagic_lib-0.1.4.dist-info/WHEEL
sagemaker_studio_sparkmagic_lib-0.1.4.dist-info/entry_points.txt
sagemaker_studio_sparkmagic_lib-0.1.4.dist-info/top_level.txt
sagemaker_studio_sparkmagic_lib-0.1.4.dist-info/RECORD
