Metadata-Version: 2.1
Name: sagemaker-studio-sparkmagic-lib
Version: 0.1.4
Summary: Python Command line tool to manage configuration of sparkmagic kernels on studio
Home-page: https://github.com/aws-samples/sagemaker-studio-sparkmagic-conf
Author: Amazon Web Services
License: MIT-0 License
Platform: UNKNOWN
Classifier: Intended Audience :: Developers
Classifier: Intended Audience :: Science/Research
Classifier: Programming Language :: Python
Classifier: Programming Language :: Python :: 3.6
Classifier: Programming Language :: Python :: 3.7
Classifier: Programming Language :: Python :: 3.8
Requires-Python: >=3.6
License-File: LICENSE
License-File: LICENSE.txt
License-File: NOTICE
Requires-Dist: boto3 (<2.0,>=1.10.44)
Provides-Extra: dev
Requires-Dist: black ; extra == 'dev'
Requires-Dist: pytest ; extra == 'dev'
